setup.py
alphaGrinder/__init__.py
alphaGrinder/alphaGrinder.py
alphaGrinder.egg-info/PKG-INFO
alphaGrinder.egg-info/SOURCES.txt
alphaGrinder.egg-info/dependency_links.txt
alphaGrinder.egg-info/top_level.txt