Metadata-Version: 2.1
Name: alphaGrinder
Version: 0.0.3
Summary: common A Share alpha and risk factors
Author: Xi
